faliceqbot/__init__.py
faliceqbot/bot.py
faliceqbot/logger.py
faliceqbot/matcher.py
faliceqbot/py.typed
faliceqbot/segments.py
faliceqbot/adapters/console.py
faliceqbot/adapters/satori.py
faliceqbot-1.0.1.dist-info/LICENSE
faliceqbot-1.0.1.dist-info/METADATA
faliceqbot-1.0.1.dist-info/WHEEL
faliceqbot-1.0.1.dist-info/top_level.txt
faliceqbot-1.0.1.dist-info/RECORD
