Metadata-Version: 2.1
Name: faliceqbot
Version: 1.0.1
Summary: A simple QQ bot written in Python
Author-email: Falsw <falsestar114514@outlook.com>
Project-URL: Homepage, https://github.com/Falsw-star/FaliceQBot-Respawn
Classifier: Programming Language :: Python :: 3
Classifier: License :: OSI Approved :: MIT License
Classifier: Operating System :: OS Independent
Requires-Python: >=3.11
License-File: LICENSE
Requires-Dist: websocket-client
